ligo_hires_gps_time-0.6.5.dist-info/METADATA
ligo_hires_gps_time-0.6.5.dist-info/WHEEL
ligo_hires_gps_time/__init__.py
ligo_hires_gps_time/__init__.pyi
ligo_hires_gps_time/ligo_hires_gps_time.cpython-313-x86_64-linux-gnu.so
ligo_hires_gps_time/py.typed
ligo_hires_gps_time-0.6.5.dist-info/RECORD
