Metadata-Version: 2.4
Name: ligo_hires_gps_time
Version: 0.6.5
Requires-Dist: cffi
Requires-Dist: gpstime ; extra == 'test'
Requires-Dist: pytest ; extra == 'test'
Provides-Extra: test
Summary: A high-resolution time library with instants taken from the GPS epoch.
Home-Page: https://git.ligo.org/cds/software/cr_tools/ligo_hires_gps_time
Author: Erik von Reis <erik.vonreis@ligo.org>
Author-email: Erik von Reis <erik.vonreis@ligo.org>
License: GPL-3.0-or-later
Requires-Python: >=3.8
Project-URL: Source Code, https://git.ligo.org/cds/software/cr_tools/ligo_hires_gps_time.git
